mdc_trace_logger/__init__.py
mdc_trace_logger/config.py
mdc_trace_logger/context.py
mdc_trace_logger/handlers.py
mdc_trace_logger/utils.py
mdc_trace_logger-0.2.0.dist-info/METADATA
mdc_trace_logger-0.2.0.dist-info/WHEEL
mdc_trace_logger-0.2.0.dist-info/licenses/LICENSE
mdc_trace_logger-0.2.0.dist-info/RECORD
