Metadata-Version: 2.4
Name: mdc-trace-logger
Version: 0.2.0
Summary: Multi-threaded MDC logging with ECS format
Project-URL: Source, https://github.com/Bulga-xD/mdc_logger
License-File: LICENSE
Classifier: License :: OSI Approved :: MIT License
Classifier: Operating System :: OS Independent
Classifier: Programming Language :: Python :: 3
Requires-Python: >=3.7
Requires-Dist: ecs-logging==2.2.0
Requires-Dist: pyyaml==6.0.2
Provides-Extra: test
Requires-Dist: black; extra == 'test'
Requires-Dist: coverage; extra == 'test'
Requires-Dist: isort[colors]; extra == 'test'
Requires-Dist: mypy; extra == 'test'
Requires-Dist: pytest; extra == 'test'
Requires-Dist: pytest-cov; extra == 'test'
